aviation_chart_server/__init__.py
aviation_chart_server/__main__.py
aviation_chart_server/chart_processor.py
aviation_chart_server/chart_server.py
aviation_chart_server/cli.py
aviation_chart_server/config/chart_service_config.default.json
aviation_chart_server/resources/shape_files/helicopter/Baltimore HEL/Baltimore HEL.cpg
aviation_chart_server/resources/shape_files/helicopter/Baltimore HEL/Baltimore HEL.dbf
aviation_chart_server/resources/shape_files/helicopter/Baltimore HEL/Baltimore HEL.prj
aviation_chart_server/resources/shape_files/helicopter/Baltimore HEL/Baltimore HEL.shp
aviation_chart_server/resources/shape_files/helicopter/Baltimore HEL/Baltimore HEL.shx
aviation_chart_server/resources/shape_files/helicopter/Boston Downtown HEL/Baltimore HEL.prj.cpg
aviation_chart_server/resources/shape_files/helicopter/Boston Downtown HEL/Baltimore HEL.prj.dbf
aviation_chart_server/resources/shape_files/helicopter/Boston Downtown HEL/Baltimore HEL.prj.prj
aviation_chart_server/resources/shape_files/helicopter/Boston Downtown HEL/Baltimore HEL.prj.shp
aviation_chart_server/resources/shape_files/helicopter/Boston Downtown HEL/Baltimore HEL.prj.shx
aviation_chart_server/resources/shape_files/helicopter/Boston HEL/Boston HEL.cpg
aviation_chart_server/resources/shape_files/helicopter/Boston HEL/Boston HEL.dbf
aviation_chart_server/resources/shape_files/helicopter/Boston HEL/Boston HEL.prj
aviation_chart_server/resources/shape_files/helicopter/Boston HEL/Boston HEL.shp
aviation_chart_server/resources/shape_files/helicopter/Boston HEL/Boston HEL.shx
aviation_chart_server/resources/shape_files/helicopter/Chicago HEL/Chicago HEL.cpg
aviation_chart_server/resources/shape_files/helicopter/Chicago HEL/Chicago HEL.dbf
aviation_chart_server/resources/shape_files/helicopter/Chicago HEL/Chicago HEL.prj
aviation_chart_server/resources/shape_files/helicopter/Chicago HEL/Chicago HEL.shp
aviation_chart_server/resources/shape_files/helicopter/Chicago HEL/Chicago HEL.shx
aviation_chart_server-1.0.5.dist-info/licenses/LICENSE
aviation_chart_server-1.0.5.dist-info/METADATA
aviation_chart_server-1.0.5.dist-info/WHEEL
aviation_chart_server-1.0.5.dist-info/entry_points.txt
aviation_chart_server-1.0.5.dist-info/top_level.txt
aviation_chart_server-1.0.5.dist-info/RECORD
