Metadata-Version: 2.4
Name: aviation-chart-server
Version: 1.0.5
Summary: A Python service for processing and serving FAA aviation charts as tile pyramids
Author-email: Roman Kozulia <romanmuni8@gmail.com>
Project-URL: Homepage, https://github.com/eightspokes/chart_processor_package
Project-URL: Documentation, https://github.com/eightspokes/chart_processor_package#readme
Project-URL: Repository, https://github.com/eightspokes/chart_processor_package
Project-URL: Bug Reports, https://github.com/eightspokes/chart_processor_package/issues
Classifier: Development Status :: 4 - Beta
Classifier: Intended Audience :: Developers
Classifier: License :: OSI Approved :: MIT License
Classifier: Operating System :: OS Independent
Classifier: Programming Language :: Python :: 3
Classifier: Programming Language :: Python :: 3.8
Classifier: Programming Language :: Python :: 3.9
Classifier: Programming Language :: Python :: 3.10
Classifier: Programming Language :: Python :: 3.11
Classifier: Topic :: Scientific/Engineering :: GIS
Classifier: Topic :: Internet :: WWW/HTTP :: HTTP Servers
Requires-Python: >=3.8
License-File: LICENSE
Requires-Dist: certifi>=2025.1.31
Requires-Dist: charset-normalizer>=3.4.1
Requires-Dist: idna>=3.10
Requires-Dist: numpy
Requires-Dist: requests>=2.32.3
Requires-Dist: urllib3>=2.3.0
Provides-Extra: gdal
Requires-Dist: gdal>=3.4.0; extra == "gdal"
Provides-Extra: dev
Requires-Dist: pytest>=7.0; extra == "dev"
Requires-Dist: black>=22.0; extra == "dev"
Requires-Dist: flake8>=4.0; extra == "dev"
Requires-Dist: mypy>=0.950; extra == "dev"
Dynamic: license-file
